osbnr/__init__.py
osbnr/osbnr.py
osbnr-0.1.2.dist-info/LICENSE
osbnr-0.1.2.dist-info/METADATA
osbnr-0.1.2.dist-info/WHEEL
osbnr-0.1.2.dist-info/top_level.txt
osbnr-0.1.2.dist-info/RECORD
