Metadata-Version: 2.1
Name: osbnr
Version: 0.1.2
Summary: One Side Behavioral Noise Reduction algorithm implementation
Home-page: UNKNOWN
Author: Salma EL HAJJAMI
Author-email: s.elhajjami@uiz.ac.ma
License: UNKNOWN
Platform: UNKNOWN
Classifier: Development Status :: 3 - Alpha
Classifier: Intended Audience :: Developers
Classifier: License :: OSI Approved :: GNU General Public License v3 (GPLv3)
Classifier: Programming Language :: Python :: 3
Classifier: Operating System :: OS Independent
License-File: LICENSE
Requires-Dist: scikit-learn
Requires-Dist: numpy
